ckanext/__init__.py
ckanext/resource_indexer/__init__.py
ckanext/resource_indexer/cli.py
ckanext/resource_indexer/config.py
ckanext/resource_indexer/exc.py
ckanext/resource_indexer/interface.py
ckanext/resource_indexer/plugin.py
ckanext/resource_indexer/utils.py
ckanext/resource_indexer/tests/__init__.py
ckanext/resource_indexer/tests/conftest.py
ckanext/resource_indexer/tests/test_plugin.py
ckanext/resource_indexer/tests/test_utils.py
ckanext_resource_indexer-0.4.2.post1.dist-info/LICENSE
ckanext_resource_indexer-0.4.2.post1.dist-info/METADATA
ckanext_resource_indexer-0.4.2.post1.dist-info/WHEEL
ckanext_resource_indexer-0.4.2.post1.dist-info/entry_points.txt
ckanext_resource_indexer-0.4.2.post1.dist-info/top_level.txt
ckanext_resource_indexer-0.4.2.post1.dist-info/RECORD
