Metadata-Version: 2.1
Name: ckanext-resource_indexer
Version: 0.4.2.post1
Author-email: DataShades <datashades@linkdigital.com.au>, Sergey Motornyuk <sergey.motornyuk@linkdigital.com.au>
Maintainer-email: DataShades <datashades@linkdigital.com.au>
License: AGPL
Project-URL: Homepage, https://github.com/DataShades/ckanext-resource_indexer
Keywords: CKAN
Classifier: Development Status :: 4 - Beta
Classifier: License :: OSI Approved :: GNU Affero General Public License v3 or later (AGPLv3+)
Classifier: Programming Language :: Python :: 3.7
Classifier: Programming Language :: Python :: 3.8
Classifier: Programming Language :: Python :: 3.9
Classifier: Programming Language :: Python :: 3.10
License-File: LICENSE
Requires-Dist: ckantoolkit
Requires-Dist: six
Provides-Extra: all
Requires-Dist: pdftotext ; extra == 'all'
Provides-Extra: dev
Requires-Dist: pdftotext ; extra == 'dev'
Requires-Dist: pytest-ckan ; extra == 'dev'
Requires-Dist: pytest-factoryboy ; extra == 'dev'
Provides-Extra: pdf
Requires-Dist: pdftotext ; extra == 'pdf'
Provides-Extra: test
Requires-Dist: pytest-ckan ; extra == 'test'
Requires-Dist: pytest-factoryboy ; extra == 'test'
